azfuncstate.py
az_func_state-0.1.1.dist-info/licenses/LICENSE
az_func_state-0.1.1.dist-info/METADATA
az_func_state-0.1.1.dist-info/WHEEL
az_func_state-0.1.1.dist-info/top_level.txt
az_func_state-0.1.1.dist-info/RECORD
