Metadata-Version: 2.4
Name: az-func-state
Version: 0.1.1
Summary: State tracking utility using Blob Storage
Author-email: Arthur Kao <aka0@outlook.com>
Maintainer-email: Arthur Kao <aka0@outlook.com>
License: MIT
Project-URL: Homepage, https://github.com/aka0/az-func-state
Project-URL: Documentation, https://github.com/aka0/az-func-state#readme
Keywords: azure,functions,state,storage,blob
Classifier: Development Status :: 4 - Beta
Classifier: Intended Audience :: Developers
Classifier: License :: OSI Approved :: MIT License
Classifier: Programming Language :: Python :: 3.12
Classifier: Operating System :: OS Independent
Classifier: Topic :: Software Development :: Libraries
Requires-Python: >=3.12
License-File: LICENSE
Requires-Dist: azure-storage-blob>=12.19.0
Dynamic: license-file
